{
  "$schema": "http://schema.management.azure.com/schemas/2015-01-01/deploymentParameters.json#",
  "contentVersion": "2019.05.01.0",
  "parameters": {
    "name": {
      "value": ""
    },
    "Network": {
      "value": {}
    },
    "applicationGatewayRules": {
      "value": []
    },
    "Size": {
      "value": ""
    },
    "Tier": {
      "value": ""
    },
    "Instances": {
      "value": 1
    },
    "RuleSet": {
      "value": "3.0"
    },
    "CustomObject": {
      "value": {}
    },
    "environment": {
      "value": ""
    },
    "buildDate": {
      "value": ""
    },
    "buildBy": {
      "value": ""
    },
    "buildTicket": {
      "value": ""
    },
    "RaxAutomationExclude": {
      "value": ""
    }
  }
}