{
  "$schema": "https://schema.management.azure.com/schemas/2015-01-01/deploymentParameters.json#",
  "contentVersion": "2019.06.01.0",
  "parameters": {
    "name": {
      "value": ""
    },
    "administratorLogin": {
      "value": ""
    },
    "administratorLoginPassword": {
      "value": ""
    },
    "sslEnforcement": {
      "value": "Enabled"
    },
    "version": {
      "value": "9.5"
    },
    "backupRetentionDays": {
      "value": 7
    },
    "geoRedundantBackup": {
      "value": "Disabled"
    },
    "storageMB": {
      "value": 5
    },
    "capacity": {
      "value": 2
    },
    "family": {
      "value": "Gen5"
    },
    "tier": {
      "value": "GeneralPurpose"
    },
    "CustomObject": {
      "value": {}
    },
    "environment": {
      "value": ""
    },
    "buildDate": {
      "value": ""
    },
    "buildBy": {
      "value": ""
    },
    "buildTicket": {
      "value": ""
    },
    "RaxAutomationExclude": {
      "value": ""
    }
  }
}